[
  {
    "club_id": "439808",
    "name": "Tony J.",
    "mile": 33.554034,
    "count": "4"
  },
  {
    "club_id": "439808",
    "name": "Howard G.",
    "mile": 31.503509700000002,
    "count": "3"
  },
  {
    "club_id": "72363",
    "name": "Grant G.",
    "mile": 31.130687100000003,
    "count": "2"
  },
  {
    "club_id": "439808",
    "name": "Jesse L.",
    "mile": 30.7578645,
    "count": "2"
  },
  {
    "club_id": "439808",
    "name": "Tony C.",
    "mile": 30.3850419,
    "count": "3"
  },
  {
    "club_id": "72363",
    "name": "Don S.",
    "mile": 30.260767700000002,
    "count": "4"
  },
  {
    "club_id": "72363",
    "name": "Guodong P.",
    "mile": 26.470404600000002,
    "count": "2"
  },
  {
    "club_id": "439808",
    "name": "May W.",
    "mile": 26.097582,
    "count": "4"
  },
  {
    "club_id": "439808",
    "name": "Richard Y.",
    "mile": 26.097582,
    "count": "3"
  },
  {
    "club_id": "301632",
    "name": "Harris Z.",
    "mile": 23.7363722,
    "count": "3"
  },
  {
    "club_id": "523602",
    "name": "Guanyu W.",
    "mile": 22.990727,
    "count": "3"
  },
  {
    "club_id": "439808",
    "name": "Wayne H.",
    "mile": 22.493630200000002,
    "count": "2"
  },
  {
    "club_id": "301632",
    "name": "Shen X.",
    "mile": 22.245081799999998,
    "count": "3"
  },
  {
    "club_id": "72363",
    "name": "Tiansong D.",
    "mile": 22.245081799999998,
    "count": "2"
  },
  {
    "club_id": "301632",
    "name": "Jason L.",
    "mile": 21.126614,
    "count": "2"
  },
  {
    "club_id": "439808",
    "name": "Samantha W.",
    "mile": 21.002339799999998,
    "count": "3"
  },
  {
    "club_id": "72363",
    "name": "Min C.",
    "mile": 20.6916543,
    "count": "3"
  },
  {
    "club_id": "301632",
    "name": "Lifeng P.",
    "mile": 20.194557500000002,
    "count": "3"
  },
  {
    "club_id": "523602",
    "name": "Hongzhe L.",
    "mile": 20.1324204,
    "count": "2"
  },
  {
    "club_id": "439808",
    "name": "Jane L.",
    "mile": 20.008146200000002,
    "count": "1"
  },
  {
    "club_id": "72363",
    "name": "Shengxi D.",
    "mile": 19.9460091,
    "count": "5"
  },
  {
    "club_id": "439808",
    "name": "Bi C.",
    "mile": 19.7595978,
    "count": "4"
  },
  {
    "club_id": "301632",
    "name": "Jingjun S.",
    "mile": 18.8896784,
    "count": "6"
  },
  {
    "club_id": "301632",
    "name": "Chunxin W.",
    "mile": 18.3304445,
    "count": "2"
  },
  {
    "club_id": "301632",
    "name": "Jessie Y.",
    "mile": 18.3304445,
    "count": "3"
  },
  {
    "club_id": "439808",
    "name": "david w.",
    "mile": 18.019759,
    "count": "3"
  },
  {
    "club_id": "523602",
    "name": "Jun S.",
    "mile": 17.895484800000002,
    "count": "3"
  },
  {
    "club_id": "72363",
    "name": "Jean C.",
    "mile": 17.646936399999998,
    "count": "2"
  },
  {
    "club_id": "72363",
    "name": "Wei T.",
    "mile": 17.3362509,
    "count": "2"
  },
  {
    "club_id": "72363",
    "name": "Dayu Z.",
    "mile": 17.274113800000002,
    "count": "7"
  },
  {
    "club_id": "72363",
    "name": "Yi G.",
    "mile": 17.1498396,
    "count": "3"
  },
  {
    "club_id": "72363",
    "name": "Ivy Z.",
    "mile": 16.839154100000002,
    "count": "2"
  },
  {
    "club_id": "523602",
    "name": "Alex L.",
    "mile": 16.777017,
    "count": "2"
  },
  {
    "club_id": "439808",
    "name": "David W.",
    "mile": 16.5284686,
    "count": "2"
  },
  {
    "club_id": "439808",
    "name": "Hong J.",
    "mile": 16.155646,
    "count": "2"
  },
  {
    "club_id": "72363",
    "name": "Wendy T.",
    "mile": 16.031371800000002,
    "count": "2"
  },
  {
    "club_id": "439808",
    "name": "Julie Q.",
    "mile": 15.9692347,
    "count": "2"
  },
  {
    "club_id": "439808",
    "name": "Min Y.",
    "mile": 15.9692347,
    "count": "2"
  },
  {
    "club_id": "439808",
    "name": "Sherry s.",
    "mile": 15.9692347,
    "count": "2"
  },
  {
    "club_id": "72363",
    "name": "Yc L.",
    "mile": 15.9070976,
    "count": "3"
  },
  {
    "club_id": "72363",
    "name": "Danrey W.",
    "mile": 15.5964121,
    "count": "1"
  },
  {
    "club_id": "439808",
    "name": "Michael Y.",
    "mile": 15.4721379,
    "count": "3"
  },
  {
    "club_id": "72363",
    "name": "Ding d.",
    "mile": 15.3478637,
    "count": "3"
  },
  {
    "club_id": "523602",
    "name": "Patrick Z.",
    "mile": 14.0429846,
    "count": "2"
  },
  {
    "club_id": "301632",
    "name": "Xuesong W.",
    "mile": 14.0429846,
    "count": "2"
  },
  {
    "club_id": "439808",
    "name": "Yunfeng Z.",
    "mile": 13.7944362,
    "count": "2"
  },
  {
    "club_id": "72363",
    "name": "Zhong O.",
    "mile": 13.608024899999998,
    "count": "2"
  },
  {
    "club_id": "523602",
    "name": "ningde x.",
    "mile": 13.608024899999998,
    "count": "2"
  },
  {
    "club_id": "439808",
    "name": "Hui W.",
    "mile": 13.545887800000001,
    "count": "3"
  },
  {
    "club_id": "72363",
    "name": "Qiong L.",
    "mile": 13.297339399999998,
    "count": "1"
  }
]