[
  {
    "club_id": "175314",
    "name": "YP Z.",
    "mile": 113.4623446,
    "count": "11"
  },
  {
    "club_id": "204946",
    "name": "🐝 J.",
    "mile": 72.38972150000001,
    "count": "10"
  },
  {
    "club_id": "241951",
    "name": "Jun W.",
    "mile": 64.3740356,
    "count": "6"
  },
  {
    "club_id": "204946",
    "name": "Bruin1996 R.",
    "mile": 62.1992371,
    "count": "15"
  },
  {
    "club_id": "241951",
    "name": "Feng Q.",
    "mile": 61.3914548,
    "count": "6"
  },
  {
    "club_id": "241951",
    "name": "Richard Y.",
    "mile": 54.9291964,
    "count": "6"
  },
  {
    "club_id": "175314",
    "name": "zhen l.",
    "mile": 50.2689139,
    "count": "8"
  },
  {
    "club_id": "241951",
    "name": "Michael Y.",
    "mile": 49.7718171,
    "count": "6"
  },
  {
    "club_id": "175314",
    "name": "Jianmin Z.",
    "mile": 49.0261719,
    "count": "8"
  },
  {
    "club_id": "204946",
    "name": "Jing W.",
    "mile": 47.969841200000005,
    "count": "5"
  },
  {
    "club_id": "241951",
    "name": "victor k.",
    "mile": 47.9077041,
    "count": "7"
  },
  {
    "club_id": "204946",
    "name": "Richard Y.",
    "mile": 46.602825,
    "count": "5"
  },
  {
    "club_id": "204946",
    "name": "🐝 Gefei X.",
    "mile": 46.230002400000004,
    "count": "5"
  },
  {
    "club_id": "176328",
    "name": "Yu L.",
    "mile": 43.558107099999994,
    "count": "5"
  },
  {
    "club_id": "204946",
    "name": "Connie Z.",
    "mile": 43.1231474,
    "count": "6"
  },
  {
    "club_id": "241951",
    "name": "john c.",
    "mile": 40.5755263,
    "count": "5"
  },
  {
    "club_id": "241951",
    "name": "Tony L.",
    "mile": 40.4512521,
    "count": "5"
  },
  {
    "club_id": "204946",
    "name": "Gan L.",
    "mile": 40.389115000000004,
    "count": "5"
  },
  {
    "club_id": "176328",
    "name": "Shufan W.",
    "mile": 39.7056069,
    "count": "9"
  },
  {
    "club_id": "241951",
    "name": "David W.",
    "mile": 39.2706472,
    "count": "4"
  },
  {
    "club_id": "241951",
    "name": "David M.",
    "mile": 39.2085101,
    "count": "7"
  },
  {
    "club_id": "241951",
    "name": "Jiang Z.",
    "mile": 38.8978246,
    "count": "6"
  },
  {
    "club_id": "241951",
    "name": "Liyi G.",
    "mile": 38.6492762,
    "count": "4"
  },
  {
    "club_id": "241951",
    "name": "Rebecca C.",
    "mile": 37.4686713,
    "count": "4"
  },
  {
    "club_id": "176328",
    "name": "Yi Z.",
    "mile": 37.4065342,
    "count": "6"
  },
  {
    "club_id": "241951",
    "name": "Minnie Z.",
    "mile": 36.7851632,
    "count": "5"
  },
  {
    "club_id": "204946",
    "name": "David Y.",
    "mile": 36.598751899999996,
    "count": "6"
  },
  {
    "club_id": "204946",
    "name": "Victor X.",
    "mile": 36.039518,
    "count": "6"
  },
  {
    "club_id": "241951",
    "name": "Frank L.",
    "mile": 35.6666954,
    "count": "4"
  },
  {
    "club_id": "241951",
    "name": "Jian Z.",
    "mile": 34.9831873,
    "count": "4"
  },
  {
    "club_id": "204946",
    "name": "Patrick (Ray) H.",
    "mile": 34.2996792,
    "count": "8"
  },
  {
    "club_id": "176328",
    "name": "Haiyong L.",
    "mile": 34.175405,
    "count": "5"
  },
  {
    "club_id": "204946",
    "name": "Yan Y.",
    "mile": 32.932663,
    "count": "8"
  },
  {
    "club_id": "241951",
    "name": "Rose L.",
    "mile": 32.435566200000004,
    "count": "6"
  },
  {
    "club_id": "176328",
    "name": "wilson z.",
    "mile": 32.311292,
    "count": "6"
  },
  {
    "club_id": "241951",
    "name": "Yulin M.",
    "mile": 31.752058100000003,
    "count": "5"
  },
  {
    "club_id": "241951",
    "name": "C T.",
    "mile": 31.5656468,
    "count": "10"
  },
  {
    "club_id": "241951",
    "name": "Chen Z.",
    "mile": 31.0064129,
    "count": "5"
  },
  {
    "club_id": "241951",
    "name": "胖 猫.",
    "mile": 30.8200016,
    "count": "4"
  },
  {
    "club_id": "175314",
    "name": "Yong W.",
    "mile": 30.3229048,
    "count": "5"
  },
  {
    "club_id": "176328",
    "name": "Fan Y.",
    "mile": 30.1986306,
    "count": "2"
  },
  {
    "club_id": "176328",
    "name": "Peter Z.",
    "mile": 29.825808000000002,
    "count": "4"
  },
  {
    "club_id": "175314",
    "name": "Sherry M.",
    "mile": 29.7636709,
    "count": "7"
  },
  {
    "club_id": "176328",
    "name": "Zhiren Z.",
    "mile": 29.7015338,
    "count": "4"
  },
  {
    "club_id": "204946",
    "name": "Junyi C.",
    "mile": 29.5772596,
    "count": "4"
  },
  {
    "club_id": "175314",
    "name": "Yuxing F.",
    "mile": 29.2665741,
    "count": "5"
  },
  {
    "club_id": "175314",
    "name": "zhenyi L.",
    "mile": 28.9558886,
    "count": "4"
  },
  {
    "club_id": "241951",
    "name": "Yuefeng T.",
    "mile": 28.8937515,
    "count": "5"
  },
  {
    "club_id": "204946",
    "name": "B. C.",
    "mile": 28.7694773,
    "count": "7"
  },
  {
    "club_id": "176328",
    "name": "Jimmy Z.",
    "mile": 27.961695,
    "count": "3"
  }
]