{
  "72363": [
    [
      "1",
      "Shengxi D.",
      "16.7 km",
      "1",
      "16.7 km",
      "5:38 /km",
      "45 m"
    ],
    [
      "2",
      "Jason L.",
      "14.8 km",
      "1",
      "14.8 km",
      "6:29 /km",
      "373 m"
    ],
    [
      "3",
      "Hon Z.",
      "12.2 km",
      "1",
      "12.2 km",
      "7:18 /km",
      "64 m"
    ],
    [
      "4",
      "Tiansong D.",
      "6.1 km",
      "1",
      "6.1 km",
      "4:55 /km",
      "25 m"
    ]
  ],
  "128445": [
    [
      "1",
      "Xinyu M.",
      "16.3 km",
      "1",
      "16.3 km",
      "5:27 /km",
      "105 m"
    ],
    [
      "2",
      "Hai Z.",
      "12.5 km",
      "1",
      "12.5 km",
      "4:57 /km",
      "77 m"
    ],
    [
      "3",
      "Siqi W.",
      "10.5 km",
      "1",
      "10.5 km",
      "4:56 /km",
      "138 m"
    ],
    [
      "4",
      "Toby S.",
      "6.7 km",
      "1",
      "6.7 km",
      "5:51 /km",
      "117 m"
    ],
    [
      "5",
      "Yi H.",
      "6.5 km",
      "1",
      "6.5 km",
      "7:10 /km",
      "16 m"
    ]
  ],
  "142275": [
    [
      "1",
      "Frank S.",
      "23.3 km",
      "1",
      "23.3 km",
      "2:58 /km",
      "21 m"
    ],
    [
      "2",
      "Ning D.",
      "13.3 km",
      "1",
      "13.3 km",
      "5:29 /km",
      "--"
    ],
    [
      "3",
      "Esther Y.",
      "12.1 km",
      "2",
      "9.6 km",
      "8:02 /km",
      "194 m"
    ],
    [
      "4",
      "Carrie L.",
      "11.7 km",
      "1",
      "11.7 km",
      "6:27 /km",
      "11 m"
    ],
    [
      "5",
      "Ray S.",
      "10.7 km",
      "1",
      "10.7 km",
      "7:12 /km",
      "25 m"
    ],
    [
      "6",
      "Jason L.",
      "10.1 km",
      "1",
      "10.1 km",
      "5:13 /km",
      "79 m"
    ],
    [
      "7",
      "Jimmy W.",
      "9.9 km",
      "1",
      "9.9 km",
      "6:23 /km",
      "--"
    ],
    [
      "8",
      "Zhili Z.",
      "9.9 km",
      "1",
      "9.9 km",
      "5:49 /km",
      "16 m"
    ],
    [
      "9",
      "Patrick P.",
      "9.6 km",
      "1",
      "9.6 km",
      "4:39 /km",
      "4 m"
    ],
    [
      "10",
      "Lynn C.",
      "9.6 km",
      "2",
      "6.4 km",
      "6:12 /km",
      "19 m"
    ],
    [
      "11",
      "Sutang C.",
      "6.4 km",
      "1",
      "6.4 km",
      "6:16 /km",
      "63 m"
    ],
    [
      "12",
      "Denise S.",
      "5.2 km",
      "1",
      "5.2 km",
      "5:54 /km",
      "40 m"
    ]
  ],
  "147066": [
    [
      "There are no results.",
      null,
      null,
      null,
      null,
      null,
      null
    ]
  ],
  "155681": [
    [
      "1",
      "Lixian H.",
      "10.1 km",
      "1",
      "10.1 km",
      "6:16 /km",
      "47 m"
    ],
    [
      "2",
      "Eric W.",
      "10.0 km",
      "1",
      "10.0 km",
      "5:44 /km",
      "278 m"
    ],
    [
      "3",
      "Min C.",
      "8.9 km",
      "2",
      "7.3 km",
      "6:15 /km",
      "33 m"
    ],
    [
      "4",
      "Lei W.",
      "8.5 km",
      "1",
      "8.5 km",
      "6:15 /km",
      "38 m"
    ],
    [
      "5",
      "Pingshan W.",
      "6.6 km",
      "1",
      "6.6 km",
      "6:29 /km",
      "7 m"
    ],
    [
      "6",
      "Xiao L.",
      "5.2 km",
      "1",
      "5.2 km",
      "5:44 /km",
      "22 m"
    ],
    [
      "7",
      "没功夫的 熊.",
      "5.0 km",
      "1",
      "5.0 km",
      "5:56 /km",
      "277 m"
    ],
    [
      "8",
      "Sunny Y.",
      "4.9 km",
      "1",
      "4.9 km",
      "6:24 /km",
      "14 m"
    ],
    [
      "9",
      "Qing J.",
      "4.0 km",
      "1",
      "4.0 km",
      "12:48 /km",
      "--"
    ],
    [
      "10",
      "Yong J.",
      "3.2 km",
      "1",
      "3.2 km",
      "7:24 /km",
      "12 m"
    ]
  ],
  "157594": [
    [
      "1",
      "Jingyang Z.",
      "12.5 km",
      "1",
      "12.5 km",
      "5:22 /km",
      "42 m"
    ]
  ],
  "175314": [
    [
      "1",
      "Fei Z.",
      "6.5 km",
      "1",
      "6.5 km",
      "6:03 /km",
      "61 m"
    ],
    [
      "2",
      "Chan F.",
      "4.5 km",
      "1",
      "4.5 km",
      "5:21 /km",
      "50 m"
    ],
    [
      "3",
      "Guodong L.",
      "2.8 km",
      "1",
      "2.8 km",
      "6:31 /km",
      "--"
    ]
  ],
  "176328": [
    [
      "1",
      "Chen H.",
      "8.0 km",
      "1",
      "8.0 km",
      "5:45 /km",
      "218 m"
    ],
    [
      "2",
      "Shufan W.",
      "7.4 km",
      "1",
      "7.4 km",
      "6:37 /km",
      "--"
    ]
  ],
  "183643": [
    [
      "1",
      "Yi H.",
      "18.0 km",
      "1",
      "18.0 km",
      "5:52 /km",
      "141 m"
    ],
    [
      "2",
      "mao Z.",
      "15.2 km",
      "1",
      "15.2 km",
      "5:18 /km",
      "230 m"
    ],
    [
      "3",
      "Snowpeak S.",
      "13.5 km",
      "1",
      "13.5 km",
      "6:08 /km",
      "157 m"
    ],
    [
      "4",
      "Kai  L.",
      "12.0 km",
      "1",
      "12.0 km",
      "7:00 /km",
      "--"
    ],
    [
      "5",
      "Sheng L.",
      "10.5 km",
      "1",
      "10.5 km",
      "5:25 /km",
      "53 m"
    ],
    [
      "6",
      "Linmin K.",
      "10.5 km",
      "1",
      "10.5 km",
      "5:25 /km",
      "53 m"
    ],
    [
      "7",
      "richard l.",
      "10.5 km",
      "1",
      "10.5 km",
      "5:49 /km",
      "70 m"
    ],
    [
      "8",
      "Binghui L.",
      "9.4 km",
      "1",
      "9.4 km",
      "5:55 /km",
      "83 m"
    ],
    [
      "9",
      "Lei W.",
      "8.5 km",
      "1",
      "8.5 km",
      "6:15 /km",
      "38 m"
    ],
    [
      "10",
      "Chang L.",
      "7.0 km",
      "1",
      "7.0 km",
      "6:24 /km",
      "8 m"
    ],
    [
      "11",
      "Yan L.",
      "6.8 km",
      "1",
      "6.8 km",
      "6:11 /km",
      "--"
    ],
    [
      "12",
      "Yi Z.",
      "5.3 km",
      "1",
      "5.3 km",
      "5:41 /km",
      "5 m"
    ],
    [
      "13",
      "Linda L.",
      "5.0 km",
      "1",
      "5.0 km",
      "7:18 /km",
      "--"
    ],
    [
      "14",
      "Jessie X.",
      "4.9 km",
      "1",
      "4.9 km",
      "6:42 /km",
      "24 m"
    ],
    [
      "15",
      "Min H.",
      "4.8 km",
      "1",
      "4.8 km",
      "8:01 /km",
      "11 m"
    ]
  ],
  "187897": [
    [
      "1",
      "Sunny C.",
      "1h 38m",
      "1",
      "--:--",
      "1h 38m",
      "--:--"
    ],
    [
      "2",
      "觀 觀.",
      "1h 19m",
      "1",
      "--:--",
      "--:--",
      "1h 19m"
    ],
    [
      "3",
      "Ryan C.",
      "1h 8m",
      "1",
      "--:--",
      "--:--",
      "1h 8m"
    ],
    [
      "4",
      "Kelvin F.",
      "54m",
      "1",
      "--:--",
      "54m",
      "--:--"
    ],
    [
      "5",
      "William R.",
      "48m",
      "1",
      "48m",
      "--:--",
      "--:--"
    ],
    [
      "6",
      "Wei Z.",
      "45m",
      "1",
      "--:--",
      "45m",
      "--:--"
    ],
    [
      "7",
      "Jie Z.",
      "41m",
      "1",
      "--:--",
      "--:--",
      "41m"
    ],
    [
      "8",
      "Alexis Z.",
      "37m",
      "1",
      "--:--",
      "--:--",
      "37m"
    ]
  ],
  "196102": [
    [
      "1",
      "Salina X.",
      "5.0 km",
      "1",
      "5.0 km",
      "8:45 /km",
      "18 m"
    ],
    [
      "2",
      "Xianqiang F.",
      "3.5 km",
      "1",
      "3.5 km",
      "6:21 /km",
      "15 m"
    ]
  ],
  "197462": [
    [
      "1",
      "Alex L.",
      "11.3 km",
      "1",
      "11.3 km",
      "5:51 /km",
      "57 m"
    ],
    [
      "2",
      "Hao H.",
      "11.3 km",
      "1",
      "11.3 km",
      "5:20 /km",
      "121 m"
    ],
    [
      "3",
      "Hong L.",
      "10.4 km",
      "1",
      "10.4 km",
      "4:56 /km",
      "74 m"
    ],
    [
      "4",
      "JiaLin C.",
      "9.8 km",
      "1",
      "9.8 km",
      "5:58 /km",
      "62 m"
    ],
    [
      "5",
      "Peng Y.",
      "9.6 km",
      "1",
      "9.6 km",
      "5:49 /km",
      "125 m"
    ],
    [
      "6",
      "Junwei L.",
      "8.6 km",
      "1",
      "8.6 km",
      "5:04 /km",
      "--"
    ],
    [
      "7",
      "Lily R.",
      "6.6 km",
      "1",
      "6.6 km",
      "6:27 /km",
      "82 m"
    ],
    [
      "8",
      "Ming Z.",
      "6.4 km",
      "1",
      "6.4 km",
      "7:03 /km",
      "31 m"
    ],
    [
      "9",
      "MiLanLan M.",
      "5.6 km",
      "1",
      "5.6 km",
      "6:33 /km",
      "99 m"
    ],
    [
      "10",
      "Qinghua W.",
      "4.4 km",
      "1",
      "4.4 km",
      "7:40 /km",
      "38 m"
    ],
    [
      "11",
      "Hong Z.",
      "3.3 km",
      "1",
      "3.3 km",
      "6:27 /km",
      "28 m"
    ],
    [
      "12",
      "Man Z.",
      "3.2 km",
      "1",
      "3.2 km",
      "7:30 /km",
      "36 m"
    ],
    [
      "13",
      "Jun L.",
      "2.0 km",
      "1",
      "2.0 km",
      "5:44 /km",
      "--"
    ]
  ],
  "204946": [
    [
      "1",
      "Yao M.",
      "9.6 km",
      "1",
      "9.6 km",
      "6:19 /km",
      "40 m"
    ]
  ],
  "229749": [
    [
      "1",
      "Jingyang Z.",
      "12.5 km",
      "1",
      "12.5 km",
      "5:22 /km",
      "42 m"
    ],
    [
      "2",
      "Henry M.",
      "8.4 km",
      "1",
      "8.4 km",
      "6:10 /km",
      "65 m"
    ],
    [
      "3",
      "Peipei Y.",
      "8.1 km",
      "1",
      "8.1 km",
      "6:16 /km",
      "81 m"
    ],
    [
      "4",
      "Chang L.",
      "7.0 km",
      "1",
      "7.0 km",
      "6:24 /km",
      "8 m"
    ],
    [
      "5",
      "胖 猫.",
      "6.4 km",
      "1",
      "6.4 km",
      "6:13 /km",
      "--"
    ],
    [
      "6",
      "Jun L.",
      "5.4 km",
      "1",
      "5.4 km",
      "5:34 /km",
      "54 m"
    ],
    [
      "7",
      "Huang J.",
      "5.2 km",
      "1",
      "5.2 km",
      "8:06 /km",
      "21 m"
    ],
    [
      "8",
      "Josh W.",
      "5.0 km",
      "1",
      "5.0 km",
      "5:59 /km",
      "--"
    ]
  ],
  "234023": [
    [
      "1",
      "Arthur G.",
      "16.8 km",
      "1",
      "16.8 km",
      "5:56 /km",
      "46 m"
    ],
    [
      "2",
      "Xianrong  W.",
      "15.3 km",
      "1",
      "15.3 km",
      "5:05 /km",
      "308 m"
    ],
    [
      "3",
      "Shizhong Y.",
      "13.0 km",
      "1",
      "13.0 km",
      "4:37 /km",
      "61 m"
    ],
    [
      "4",
      "Connie C.",
      "11.6 km",
      "1",
      "11.6 km",
      "6:23 /km",
      "59 m"
    ],
    [
      "5",
      "Melissa Q.",
      "9.8 km",
      "1",
      "9.8 km",
      "5:25 /km",
      "137 m"
    ],
    [
      "6",
      "Fucheng R.",
      "8.6 km",
      "2",
      "8.4 km",
      "5:14 /km",
      "18 m"
    ],
    [
      "7",
      "Jesse L.",
      "7.6 km",
      "1",
      "7.6 km",
      "5:04 /km",
      "53 m"
    ],
    [
      "8",
      "Kun S.",
      "7.4 km",
      "1",
      "7.4 km",
      "11:47 /km",
      "14 m"
    ],
    [
      "9",
      "Charles H.",
      "5.4 km",
      "1",
      "5.4 km",
      "6:00 /km",
      "8 m"
    ],
    [
      "10",
      "Lucy L.",
      "4.8 km",
      "1",
      "4.8 km",
      "6:28 /km",
      "33 m"
    ],
    [
      "11",
      "Veronica W.",
      "4.8 km",
      "1",
      "4.8 km",
      "5:30 /km",
      "25 m"
    ],
    [
      "12",
      "Jun Y.",
      "0.7 km",
      "1",
      "0.7 km",
      "7:09 /km",
      "9 m"
    ]
  ],
  "236304": [
    [
      "1",
      "黑山 老.",
      "16.6 km",
      "1",
      "16.6 km",
      "6:12 /km",
      "125 m"
    ],
    [
      "2",
      "Ying L.",
      "16.1 km",
      "1",
      "16.1 km",
      "7:09 /km",
      "215 m"
    ],
    [
      "3",
      "Chunxin W.",
      "13.8 km",
      "2",
      "10.3 km",
      "5:29 /km",
      "183 m"
    ],
    [
      "4",
      "Fang J.",
      "8.4 km",
      "1",
      "8.4 km",
      "4:32 /km",
      "--"
    ],
    [
      "5",
      "Annie C.",
      "3.0 km",
      "1",
      "3.0 km",
      "6:09 /km",
      "24 m"
    ]
  ],
  "241951": [
    [
      "1",
      "Michael Y.",
      "10.2 km",
      "1",
      "10.2 km",
      "4:32 /km",
      "39 m"
    ],
    [
      "2",
      "Yubin L.",
      "9.7 km",
      "1",
      "9.7 km",
      "7:06 /km",
      "75 m"
    ],
    [
      "3",
      "大 山.",
      "8.7 km",
      "1",
      "8.7 km",
      "6:53 /km",
      "27 m"
    ],
    [
      "4",
      "Jun J.",
      "8.2 km",
      "1",
      "8.2 km",
      "5:44 /km",
      "33 m"
    ],
    [
      "5",
      "Richard Y.",
      "6.8 km",
      "1",
      "6.8 km",
      "6:43 /km",
      "--"
    ],
    [
      "6",
      "胖 猫.",
      "6.4 km",
      "1",
      "6.4 km",
      "6:13 /km",
      "--"
    ],
    [
      "7",
      "蘇三 島.",
      "5.5 km",
      "1",
      "5.5 km",
      "7:12 /km",
      "16 m"
    ],
    [
      "8",
      "He T.",
      "5.2 km",
      "1",
      "5.2 km",
      "7:30 /km",
      "6 m"
    ],
    [
      "9",
      " weiguo  .",
      "1.4 km",
      "1",
      "1.4 km",
      "5:57 /km",
      "--"
    ]
  ],
  "299365": [
    [
      "There are no results.",
      null,
      null,
      null,
      null,
      null,
      null
    ]
  ],
  "301632": [
    [
      "1",
      "Chunxin W.",
      "13.8 km",
      "2",
      "10.3 km",
      "5:29 /km",
      "183 m"
    ],
    [
      "2",
      "Yong C.",
      "11.7 km",
      "1",
      "11.7 km",
      "5:40 /km",
      "74 m"
    ],
    [
      "3",
      "Harris Z.",
      "9.1 km",
      "1",
      "9.1 km",
      "5:06 /km",
      "78 m"
    ],
    [
      "4",
      "Annie C.",
      "3.0 km",
      "1",
      "3.0 km",
      "6:09 /km",
      "24 m"
    ]
  ],
  "302045": [
    [
      "There are no results.",
      null,
      null,
      null,
      null,
      null,
      null
    ]
  ],
  "327007": [
    [
      "1",
      "Yao M.",
      "9.6 km",
      "1",
      "9.6 km",
      "6:19 /km",
      "40 m"
    ],
    [
      "2",
      "May W.",
      "7.5 km",
      "1",
      "7.5 km",
      "9:45 /km",
      "34 m"
    ],
    [
      "3",
      "Richard Y.",
      "6.8 km",
      "1",
      "6.8 km",
      "6:43 /km",
      "--"
    ],
    [
      "4",
      "胖 猫.",
      "6.4 km",
      "1",
      "6.4 km",
      "6:13 /km",
      "--"
    ],
    [
      "5",
      "James C.",
      "6.1 km",
      "1",
      "6.1 km",
      "6:18 /km",
      "21 m"
    ],
    [
      "6",
      "Rebecca T.",
      "4.8 km",
      "1",
      "4.8 km",
      "5:50 /km",
      "7 m"
    ],
    [
      "7",
      "Ann Y.",
      "4.0 km",
      "1",
      "4.0 km",
      "7:50 /km",
      "69 m"
    ]
  ],
  "330129": [
    [
      "1",
      "Mariah H.",
      "11.8 km",
      "1",
      "11.8 km",
      "5:30 /km",
      "25 m"
    ],
    [
      "2",
      "Alex L.",
      "11.3 km",
      "1",
      "11.3 km",
      "5:51 /km",
      "57 m"
    ],
    [
      "3",
      "Hao H.",
      "11.3 km",
      "1",
      "11.3 km",
      "5:20 /km",
      "121 m"
    ],
    [
      "4",
      "Jing L.",
      "11.0 km",
      "1",
      "11.0 km",
      "6:41 /km",
      "98 m"
    ],
    [
      "5",
      "NAIDONG W.",
      "10.0 km",
      "1",
      "10.0 km",
      "5:38 /km",
      "96 m"
    ],
    [
      "6",
      "JiaLin C.",
      "9.8 km",
      "1",
      "9.8 km",
      "5:58 /km",
      "62 m"
    ],
    [
      "7",
      "Ying J.",
      "9.6 km",
      "1",
      "9.6 km",
      "6:05 /km",
      "81 m"
    ],
    [
      "8",
      "Lily R.",
      "6.6 km",
      "1",
      "6.6 km",
      "6:27 /km",
      "82 m"
    ],
    [
      "9",
      "Zheng B.",
      "6.5 km",
      "1",
      "6.5 km",
      "5:15 /km",
      "54 m"
    ],
    [
      "10",
      "Ligeng Y.",
      "5.6 km",
      "1",
      "5.6 km",
      "5:15 /km",
      "78 m"
    ],
    [
      "11",
      "MiLanLan M.",
      "5.6 km",
      "1",
      "5.6 km",
      "6:33 /km",
      "99 m"
    ],
    [
      "12",
      "Hua L.",
      "4.8 km",
      "1",
      "4.8 km",
      "7:26 /km",
      "62 m"
    ]
  ],
  "438046": [
    [
      "1",
      "Jian J.",
      "5.0 km",
      "1",
      "5.0 km",
      "6:25 /km",
      "47 m"
    ]
  ],
  "439808": [
    [
      "1",
      "Min Y.",
      "10.4 km",
      "1",
      "10.4 km",
      "5:31 /km",
      "40 m"
    ],
    [
      "2",
      "Lijiao D.",
      "10.1 km",
      "1",
      "10.1 km",
      "7:20 /km",
      "24 m"
    ],
    [
      "3",
      "大 山.",
      "8.7 km",
      "1",
      "8.7 km",
      "6:53 /km",
      "27 m"
    ],
    [
      "4",
      "Henry M.",
      "8.4 km",
      "1",
      "8.4 km",
      "6:10 /km",
      "65 m"
    ],
    [
      "5",
      "May W.",
      "7.5 km",
      "1",
      "7.5 km",
      "9:45 /km",
      "34 m"
    ],
    [
      "6",
      "Richard Y.",
      "6.8 km",
      "1",
      "6.8 km",
      "6:43 /km",
      "--"
    ],
    [
      "7",
      "James C.",
      "6.1 km",
      "1",
      "6.1 km",
      "6:18 /km",
      "21 m"
    ],
    [
      "8",
      "Wei G.",
      "5.6 km",
      "1",
      "5.6 km",
      "5:56 /km",
      "27 m"
    ]
  ],
  "452045": [
    [
      "1",
      "Maixing A.",
      "11.9 km",
      "1",
      "11.9 km",
      "4:53 /km",
      "42 m"
    ],
    [
      "2",
      "NAIDONG W.",
      "10.0 km",
      "1",
      "10.0 km",
      "5:38 /km",
      "96 m"
    ],
    [
      "3",
      "Jun J.",
      "8.2 km",
      "1",
      "8.2 km",
      "5:44 /km",
      "33 m"
    ],
    [
      "4",
      "胖 猫.",
      "6.4 km",
      "1",
      "6.4 km",
      "6:13 /km",
      "--"
    ],
    [
      "5",
      "Andrew M.",
      "5.4 km",
      "1",
      "5.4 km",
      "4:44 /km",
      "3 m"
    ]
  ],
  "464836": [
    [
      "1",
      "Jen L.",
      "12.0 km",
      "1",
      "12.0 km",
      "6:24 /km",
      "54 m"
    ],
    [
      "2",
      "觀 觀.",
      "12.0 km",
      "1",
      "12.0 km",
      "6:36 /km",
      "15 m"
    ],
    [
      "3",
      "Ryan C.",
      "10.0 km",
      "1",
      "10.0 km",
      "6:53 /km",
      "93 m"
    ],
    [
      "4",
      "Yi X.",
      "6.5 km",
      "1",
      "6.5 km",
      "6:10 /km",
      "16 m"
    ],
    [
      "5",
      "Joy 乔.",
      "6.4 km",
      "1",
      "6.4 km",
      "7:16 /km",
      "33 m"
    ],
    [
      "6",
      "Alexis Z.",
      "6.0 km",
      "1",
      "6.0 km",
      "6:19 /km",
      "25 m"
    ],
    [
      "7",
      "Jie Z.",
      "5.4 km",
      "1",
      "5.4 km",
      "7:37 /km",
      "92 m"
    ]
  ],
  "479503": [
    [
      "1",
      "teman s.",
      "10.2 km",
      "1",
      "10.2 km",
      "11:23 /km",
      "55 m"
    ],
    [
      "2",
      "Lei W.",
      "8.5 km",
      "1",
      "8.5 km",
      "6:15 /km",
      "38 m"
    ],
    [
      "3",
      "Susan S.",
      "7.1 km",
      "1",
      "7.1 km",
      "8:10 /km",
      "59 m"
    ],
    [
      "4",
      "Digimaniac T.",
      "4.8 km",
      "1",
      "4.8 km",
      "5:27 /km",
      "17 m"
    ]
  ],
  "481356": [
    [
      "1",
      "Andrew L.",
      "8.2 km",
      "1",
      "8.2 km",
      "5:48 /km",
      "24 m"
    ],
    [
      "2",
      "Cazuza \".",
      "7.6 km",
      "1",
      "7.6 km",
      "6:39 /km",
      "58 m"
    ],
    [
      "3",
      "Tina Y.",
      "5.0 km",
      "1",
      "5.0 km",
      "6:04 /km",
      "63 m"
    ]
  ],
  "484248": [
    [
      "1",
      "Yuhua G.",
      "15.2 km",
      "1",
      "15.2 km",
      "6:21 /km",
      "98 m"
    ],
    [
      "2",
      "Paul D.",
      "10.0 km",
      "1",
      "10.0 km",
      "5:09 /km",
      "21 m"
    ],
    [
      "3",
      "楠 安.",
      "6.9 km",
      "1",
      "6.9 km",
      "5:25 /km",
      "21 m"
    ],
    [
      "4",
      "Xinya Z.",
      "6.6 km",
      "1",
      "6.6 km",
      "5:42 /km",
      "59 m"
    ]
  ],
  "513442": [
    [
      "1",
      "Yi H.",
      "18.0 km",
      "1",
      "18.0 km",
      "5:52 /km",
      "141 m"
    ],
    [
      "2",
      "Esther Y.",
      "12.1 km",
      "2",
      "9.6 km",
      "8:02 /km",
      "194 m"
    ],
    [
      "3",
      "Maixing A.",
      "11.9 km",
      "1",
      "11.9 km",
      "4:53 /km",
      "42 m"
    ],
    [
      "4",
      "Min Y.",
      "10.4 km",
      "1",
      "10.4 km",
      "5:31 /km",
      "40 m"
    ],
    [
      "5",
      "Lei W.",
      "8.5 km",
      "1",
      "8.5 km",
      "6:15 /km",
      "38 m"
    ],
    [
      "6",
      "Jun J.",
      "8.2 km",
      "1",
      "8.2 km",
      "5:44 /km",
      "33 m"
    ],
    [
      "7",
      "May W.",
      "7.5 km",
      "1",
      "7.5 km",
      "9:45 /km",
      "34 m"
    ],
    [
      "8",
      "Qing J.",
      "4.0 km",
      "1",
      "4.0 km",
      "12:48 /km",
      "--"
    ],
    [
      "9",
      "Annie C.",
      "3.0 km",
      "1",
      "3.0 km",
      "6:09 /km",
      "24 m"
    ]
  ],
  "516025": [
    [
      "1",
      "Frank L.",
      "9.9 km",
      "1",
      "9.9 km",
      "5:50 /km",
      "--"
    ],
    [
      "2",
      "Jiang S.",
      "9.6 km",
      "1",
      "9.6 km",
      "5:44 /km",
      "--"
    ],
    [
      "3",
      "Amos L.",
      "9.6 km",
      "1",
      "9.6 km",
      "5:08 /km",
      "49 m"
    ]
  ],
  "519388": [
    [
      "1",
      "Maixing A.",
      "11.9 km",
      "1",
      "11.9 km",
      "4:53 /km",
      "42 m"
    ],
    [
      "2",
      "Jun J.",
      "8.2 km",
      "1",
      "8.2 km",
      "5:44 /km",
      "33 m"
    ],
    [
      "3",
      "May W.",
      "7.5 km",
      "1",
      "7.5 km",
      "9:45 /km",
      "34 m"
    ]
  ],
  "523430": [
    [
      "1",
      "Min Y.",
      "10.4 km",
      "1",
      "10.4 km",
      "5:31 /km",
      "40 m"
    ],
    [
      "2",
      "Henry M.",
      "8.4 km",
      "1",
      "8.4 km",
      "6:10 /km",
      "65 m"
    ],
    [
      "3",
      "May W.",
      "7.5 km",
      "1",
      "7.5 km",
      "9:45 /km",
      "34 m"
    ],
    [
      "4",
      "James C.",
      "6.1 km",
      "1",
      "6.1 km",
      "6:18 /km",
      "21 m"
    ]
  ],
  "523602": [
    [
      "There are no results.",
      null,
      null,
      null,
      null,
      null,
      null
    ]
  ]
}